ankistats/__init__.py
ankistats/plots.py
ankistats/simulation.py
ankistats/stats.py
ankistats/tables.py
ankistats-0.2.3.dist-info/LICENSE
ankistats-0.2.3.dist-info/METADATA
ankistats-0.2.3.dist-info/WHEEL
ankistats-0.2.3.dist-info/top_level.txt
ankistats-0.2.3.dist-info/RECORD
