Metadata-Version: 2.1
Name: ankistats
Version: 0.2.3
Summary: Python package to make it easier to analyse an anki database.
Home-page: https://github.com/nogira/anki-stats
Author: nogira
License: MIT
Platform: UNKNOWN
License-File: LICENSE
Requires-Dist: pandas
Requires-Dist: seaborn
